Workbook

Sheet Presupuesto
A1: PRESUPUESTO DE IMPORTACIÓN (PROVISORIO)
A2: Cliente: | F2: Contenedor:
A3: CUIT: | F3: ETD / ETA:
A4: Detalle pedido: | F4: Carrier:
A5: Origen / Cond. Venta: | F5: Freetime:
A7: RESUMEN DE LA OPERACIÓN
B8: USD | C8: ARS
A9: ① Mercadería + costo financiero | B9: =E33+E34 -> 0 | C9: =B9*B$86 -> 0
A10: ② Tributos VEP (pago a AFIP) | B10: =B82 -> 10 | C10: =C82 -> 15100
A11: ③ Gastos operativos + IVA | B11: =D103+C123 -> 0 | C11: =E103+D123 -> 0
A12: TOTAL DESEMBOLSADO (c/IVA) | B12: =B126 -> 10 | C12: =C126 -> 15100
A13: Costo total s/IVA y percepciones | B13: =B127 -> 10 | C13: =C127 -> 15100
A14: Incidencia s/FOB | B14: =IF(E33>0,(B10+B11)/E33,0) -> 0
A16: DETALLE DE MERCADERÍA
A17: Descripción | B17: NCM | C17: FOB Unit. | D17: Cant | E17: FOB Total | F17: FOB Decl.U | G17: FOB Decl.T | H17: % Partic | I17: Peso/Vol
C18: 0 | D18: 0 | E18: =C18*D18 -> 0 | F18: 0 | G18: =F18*D18 -> 0 | H18: =IF(G$33>0,G18/G$33,0) -> 0 | I18: 0
C19: 0 | D19: 0 | E19: =C19*D19 -> 0 | F19: 0 | G19: =F19*D19 -> 0 | H19: =IF(G$33>0,G19/G$33,0) -> 0 | I19: 0
C20: 0 | D20: 0 | E20: =C20*D20 -> 0 | F20: 0 | G20: =F20*D20 -> 0 | H20: =IF(G$33>0,G20/G$33,0) -> 0 | I20: 0
C21: 0 | D21: 0 | E21: =C21*D21 -> 0 | F21: 0 | G21: =F21*D21 -> 0 | H21: =IF(G$33>0,G21/G$33,0) -> 0 | I21: 0
C22: 0 | D22: 0 | E22: =C22*D22 -> 0 | F22: 0 | G22: =F22*D22 -> 0 | H22: =IF(G$33>0,G22/G$33,0) -> 0 | I22: 0
C23: 0 | D23: 0 | E23: =C23*D23 -> 0 | F23: 0 | G23: =F23*D23 -> 0 | H23: =IF(G$33>0,G23/G$33,0) -> 0 | I23: 0
C24: 0 | D24: 0 | E24: =C24*D24 -> 0 | F24: 0 | G24: =F24*D24 -> 0 | H24: =IF(G$33>0,G24/G$33,0) -> 0 | I24: 0
C25: 0 | D25: 0 | E25: =C25*D25 -> 0 | F25: 0 | G25: =F25*D25 -> 0 | H25: =IF(G$33>0,G25/G$33,0) -> 0 | I25: 0
C26: 0 | D26: 0 | E26: =C26*D26 -> 0 | F26: 0 | G26: =F26*D26 -> 0 | H26: =IF(G$33>0,G26/G$33,0) -> 0 | I26: 0
C27: 0 | D27: 0 | E27: =C27*D27 -> 0 | F27: 0 | G27: =F27*D27 -> 0 | H27: =IF(G$33>0,G27/G$33,0) -> 0 | I27: 0
C28: 0 | D28: 0 | E28: =C28*D28 -> 0 | F28: 0 | G28: =F28*D28 -> 0 | H28: =IF(G$33>0,G28/G$33,0) -> 0 | I28: 0
C29: 0 | D29: 0 | E29: =C29*D29 -> 0 | F29: 0 | G29: =F29*D29 -> 0 | H29: =IF(G$33>0,G29/G$33,0) -> 0 | I29: 0
... C32: 0 | D32: 0 | E32: =C32*D32 -> 0 | F32: 0 | G32: =F32*D32 -> 0 | H32: =IF(G$33>0,G32/G$33,0) -> 0 | I32: 0
A33: TOTAL FOB | C33: FOB Pagado: | E33: =SUM(E18:E32) -> 0 | F33: FOB Declarado: | G33: =SUM(G18:G32) -> 0 | H33: Peso Total: | I33: =SUM(I18:I32) -> 0
A34: Costo financiero | C34: 0.025 | D34: Recargo: | E34: =E33*C34 -> 0 | F34: FOB + Finan: | G34: =E33+E34 -> 0
A36: VALOR DECLARADO EN ADUANA
A37: TC Tributos: | B37: 1510 | C37: Cotización del despacho
A38: FOB declarado | B38: =G33 -> 0 | C38: =B38*B$37 -> 0
A39: Flete declarado | B39: =D88/2 -> 0 | C39: =B39*B$37 -> 0
A40: Seguro declarado | B40: =E33*0.3% -> 0 | C40: =B40*B$37 -> 0
A41: CIF DECLARADO | B41: =SUM(B38:B40) -> 0 | C41: =B41*B$37 -> 0
A43: DERECHOS, TASAS Y ANTIDUMPING
A44: Producto | B44: CIF Producto | C44: %Der | D44: Derechos | E44: %Tasa | F44: Tasa Est. | G44: %Antid | H44: Antidump. | I44: Subtotal
A45: =A18 | B45: =G18+(B$39+B$40)*H18 -> 0 | C45: 0 | D45: =B45*C45 -> 0 | E45: 0.03 | F45: =B45*E45 -> 0 | G45: 0 | H45: =B45*G45 -> 0 | I45: =D45+F45+H45 -> 0
A46: =A19 | B46: =G19+(B$39+B$40)*H19 -> 0 | C46: 0 | D46: =B46*C46 -> 0 | E46: 0.03 | F46: =B46*E46 -> 0 | G46: 0 | H46: =B46*G46 -> 0 | I46: =D46+F46+H46 -> 0
A47: =A20 | B47: =G20+(B$39+B$40)*H20 -> 0 | C47: 0 | D47: =B47*C47 -> 0 | E47: 0.03 | F47: =B47*E47 -> 0 | G47: 0 | H47: =B47*G47 -> 0 | I47: =D47+F47+H47 -> 0
A48: =A21 | B48: =G21+(B$39+B$40)*H21 -> 0 | C48: 0 | D48: =B48*C48 -> 0 | E48: 0.03 | F48: =B48*E48 -> 0 | G48: 0 | H48: =B48*G48 -> 0 | I48: =D48+F48+H48 -> 0
A49: =A22 | B49: =G22+(B$39+B$40)*H22 -> 0 | C49: 0 | D49: =B49*C49 -> 0 | E49: 0.03 | F49: =B49*E49 -> 0 | G49: 0 | H49: =B49*G49 -> 0 | I49: =D49+F49+H49 -> 0
A50: =A23 | B50: =G23+(B$39+B$40)*H23 -> 0 | C50: 0 | D50: =B50*C50 -> 0 | E50: 0.03 | F50: =B50*E50 -> 0 | G50: 0 | H50: =B50*G50 -> 0 | I50: =D50+F50+H50 -> 0
A51: =A24 | B51: =G24+(B$39+B$40)*H24 -> 0 | C51: 0 | D51: =B51*C51 -> 0 | E51: 0.03 | F51: =B51*E51 -> 0 | G51: 0 | H51: =B51*G51 -> 0 | I51: =D51+F51+H51 -> 0
A52: =A25 | B52: =G25+(B$39+B$40)*H25 -> 0 | C52: 0 | D52: =B52*C52 -> 0 | E52: 0.03 | F52: =B52*E52 -> 0 | G52: 0 | H52: =B52*G52 -> 0 | I52: =D52+F52+H52 -> 0
A53: =A26 | B53: =G26+(B$39+B$40)*H26 -> 0 | C53: 0 | D53: =B53*C53 -> 0 | E53: 0.03 | F53: =B53*E53 -> 0 | G53: 0 | H53: =B53*G53 -> 0 | I53: =D53+F53+H53 -> 0
A54: =A27 | B54: =G27+(B$39+B$40)*H27 -> 0 | C54: 0 | D54: =B54*C54 -> 0 | E54: 0.03 | F54: =B54*E54 -> 0 | G54: 0 | H54: =B54*G54 -> 0 | I54: =D54+F54+H54 -> 0
A55: =A28 | B55: =G28+(B$39+B$40)*H28 -> 0 | C55: 0 | D55: =B55*C55 -> 0 | E55: 0.03 | F55: =B55*E55 -> 0 | G55: 0 | H55: =B55*G55 -> 0 | I55: =D55+F55+H55 -> 0
A56: =A29 | B56: =G29+(B$39+B$40)*H29 -> 0 | C56: 0 | D56: =B56*C56 -> 0 | E56: 0.03 | F56: =B56*E56 -> 0 | G56: 0 | H56: =B56*G56 -> 0 | I56: =D56+F56+H56 -> 0
... A59: =A32 | B59: =G32+(B$39+B$40)*H32 -> 0 | C59: 0 | D59: =B59*C59 -> 0 | E59: 0.03 | F59: =B59*E59 -> 0 | G59: 0 | H59: =B59*G59 -> 0 | I59: =D59+F59+H59 -> 0
A60: SUBTOTAL DER+TASAS | B60: =SUM(B45:B59) -> 0 | D60: =SUM(D45:D59) -> 0 | F60: =SUM(F45:F59) -> 0 | H60: =SUM(H45:H59) -> 0 | I60: =SUM(I45:I59) -> 0
A61: BASE IVA TOTAL | B61: =B41+I60 -> 0 | C61: =B61*B$37 -> 0
A63: IMPUESTOS POR PRODUCTO
A64: Producto | B64: Base IVA Prod. | C64: %IVA | D64: IVA | E64: %IVA Ad | F64: IVA Ad | G64: %Gcias | H64: Gcias | I64: %IIBB | J64: IIBB | K64: Subtotal
A65: =A18 | B65: =B45+I45 -> 0 | C65: 0.21 | D65: =B65*C65 -> 0 | E65: 0 | F65: =B65*E65 -> 0 | G65: 0 | H65: =B65*G65 -> 0 | I65: 0.05 | J65: =B65*I65 -> 0 | K65: =D65+F65+H65+J65 -> 0
A66: =A19 | B66: =B46+I46 -> 0 | C66: 0.21 | D66: =B66*C66 -> 0 | E66: 0 | F66: =B66*E66 -> 0 | G66: 0 | H66: =B66*G66 -> 0 | I66: 0.05 | J66: =B66*I66 -> 0 | K66: =D66+F66+H66+J66 -> 0
A67: =A20 | B67: =B47+I47 -> 0 | C67: 0.21 | D67: =B67*C67 -> 0 | E67: 0 | F67: =B67*E67 -> 0 | G67: 0 | H67: =B67*G67 -> 0 | I67: 0.05 | J67: =B67*I67 -> 0 | K67: =D67+F67+H67+J67 -> 0
A68: =A21 | B68: =B48+I48 -> 0 | C68: 0.21 | D68: =B68*C68 -> 0 | E68: 0 | F68: =B68*E68 -> 0 | G68: 0 | H68: =B68*G68 -> 0 | I68: 0.05 | J68: =B68*I68 -> 0 | K68: =D68+F68+H68+J68 -> 0
A69: =A22 | B69: =B49+I49 -> 0 | C69: 0.21 | D69: =B69*C69 -> 0 | E69: 0 | F69: =B69*E69 -> 0 | G69: 0 | H69: =B69*G69 -> 0 | I69: 0.05 | J69: =B69*I69 -> 0 | K69: =D69+F69+H69+J69 -> 0
A70: =A23 | B70: =B50+I50 -> 0 | C70: 0.21 | D70: =B70*C70 -> 0 | E70: 0 | F70: =B70*E70 -> 0 | G70: 0 | H70: =B70*G70 -> 0 | I70: 0.05 | J70: =B70*I70 -> 0 | K70: =D70+F70+H70+J70 -> 0
A71: =A24 | B71: =B51+I51 -> 0 | C71: 0.21 | D71: =B71*C71 -> 0 | E71: 0 | F71: =B71*E71 -> 0 | G71: 0 | H71: =B71*G71 -> 0 | I71: 0.05 | J71: =B71*I71 -> 0 | K71: =D71+F71+H71+J71 -> 0
A72: =A25 | B72: =B52+I52 -> 0 | C72: 0.21 | D72: =B72*C72 -> 0 | E72: 0 | F72: =B72*E72 -> 0 | G72: 0 | H72: =B72*G72 -> 0 | I72: 0.05 | J72: =B72*I72 -> 0 | K72: =D72+F72+H72+J72 -> 0
A73: =A26 | B73: =B53+I53 -> 0 | C73: 0.21 | D73: =B73*C73 -> 0 | E73: 0 | F73: =B73*E73 -> 0 | G73: 0 | H73: =B73*G73 -> 0 | I73: 0.05 | J73: =B73*I73 -> 0 | K73: =D73+F73+H73+J73 -> 0
A74: =A27 | B74: =B54+I54 -> 0 | C74: 0.21 | D74: =B74*C74 -> 0 | E74: 0 | F74: =B74*E74 -> 0 | G74: 0 | H74: =B74*G74 -> 0 | I74: 0.05 | J74: =B74*I74 -> 0 | K74: =D74+F74+H74+J74 -> 0
A75: =A28 | B75: =B55+I55 -> 0 | C75: 0.21 | D75: =B75*C75 -> 0 | E75: 0 | F75: =B75*E75 -> 0 | G75: 0 | H75: =B75*G75 -> 0 | I75: 0.05 | J75: =B75*I75 -> 0 | K75: =D75+F75+H75+J75 -> 0
A76: =A29 | B76: =B56+I56 -> 0 | C76: 0.21 | D76: =B76*C76 -> 0 | E76: 0 | F76: =B76*E76 -> 0 | G76: 0 | H76: =B76*G76 -> 0 | I76: 0.05 | J76: =B76*I76 -> 0 | K76: =D76+F76+H76+J76 -> 0
... A79: =A32 | B79: =B59+I59 -> 0 | C79: 0.21 | D79: =B79*C79 -> 0 | E79: 0 | F79: =B79*E79 -> 0 | G79: 0 | H79: =B79*G79 -> 0 | I79: 0.05 | J79: =B79*I79 -> 0 | K79: =D79+F79+H79+J79 -> 0
A80: SUBTOTAL IMPUESTOS | D80: =SUM(D65:D79) -> 0 | F80: =SUM(F65:F79) -> 0 | H80: =SUM(H65:H79) -> 0 | J80: =SUM(J65:J79) -> 0 | K80: =SUM(K65:K79) -> 0
A81: Arancel SIM | B81: 10 | C81: =B81*B$37 -> 15100
A82: TOTAL TRIBUTOS VEP | B82: =I60+K80+B81 -> 10 | C82: =B82*B$37 -> 15100
A85: COSTOS OPERATIVOS
A86: TC Operativos: | B86: 1560 | C86: TC del día de pago
A87: Concepto | B87: Moneda | C87: Monto (s/IVA) | D87: USD | E87: ARS | F87: Prorrateo | G87: IVA incl.
A88: Flete | B88: USD | C88: 0 | D88: =IF(B88="USD",IF(G88="SI",C88/1.21,C88),IF(B$86>0,IF(G88="SI",C88/1.21,C88)/B$86,0)) -> 0 | E88: =IF(B88="ARS",IF(G88="SI",C88/1.21,C88),IF(G88="SI",C88/1.21,C88)*B$86) -> 0 | F88: PESO | G88: NO
A89: Seguro | B89: USD | C89: =E33*0.3% -> 0 | D89: =IF(B89="USD",IF(G89="SI",C89/1.21,C89),IF(B$86>0,IF(G89="SI",C89/1.21,C89)/B$86,0)) -> 0 | E89: =IF(B89="ARS",IF(G89="SI",C89/1.21,C89),IF(G89="SI",C89/1.21,C89)*B$86) -> 0 | F89: FOB | G89: NO
A90: Gastos EXW | B90: USD | C90: 0 | D90: =IF(B90="USD",IF(G90="SI",C90/1.21,C90),IF(B$86>0,IF(G90="SI",C90/1.21,C90)/B$86,0)) -> 0 | E90: =IF(B90="ARS",IF(G90="SI",C90/1.21,C90),IF(G90="SI",C90/1.21,C90)*B$86) -> 0 | F90: FOB | G90: NO
A91: Gastos locales | B91: USD | C91: 0 | D91: =IF(B91="USD",IF(G91="SI",C91/1.21,C91),IF(B$86>0,IF(G91="SI",C91/1.21,C91)/B$86,0)) -> 0 | E91: =IF(B91="ARS",IF(G91="SI",C91/1.21,C91),IF(G91="SI",C91/1.21,C91)*B$86) -> 0 | F91: FOB | G91: NO
A92: Terminal portuaria | B92: USD | C92: 0 | D92: =IF(B92="USD",IF(G92="SI",C92/1.21,C92),IF(B$86>0,IF(G92="SI",C92/1.21,C92)/B$86,0)) -> 0 | E92: =IF(B92="ARS",IF(G92="SI",C92/1.21,C92),IF(G92="SI",C92/1.21,C92)*B$86) -> 0 | F92: PESO | G92: NO
A93: Depósito fiscal | B93: USD | C93: 0 | D93: =IF(B93="USD",IF(G93="SI",C93/1.21,C93),IF(B$86>0,IF(G93="SI",C93/1.21,C93)/B$86,0)) -> 0 | E93: =IF(B93="ARS",IF(G93="SI",C93/1.21,C93),IF(G93="SI",C93/1.21,C93)*B$86) -> 0 | F93: PESO | G93: NO
A94: Gastos adicionales | B94: USD | C94: 0 | D94: =IF(B94="USD",IF(G94="SI",C94/1.21,C94),IF(B$86>0,IF(G94="SI",C94/1.21,C94)/B$86,0)) -> 0 | E94: =IF(B94="ARS",IF(G94="SI",C94/1.21,C94),IF(G94="SI",C94/1.21,C94)*B$86) -> 0 | F94: PESO | G94: NO
A95: Gestiones terceros organismos | B95: USD | C95: 0 | D95: =IF(B95="USD",IF(G95="SI",C95/1.21,C95),IF(B$86>0,IF(G95="SI",C95/1.21,C95)/B$86,0)) -> 0 | E95: =IF(B95="ARS",IF(G95="SI",C95/1.21,C95),IF(G95="SI",C95/1.21,C95)*B$86) -> 0 | F95: PESO | G95: NO
A96: Traslado interno (en ARS) | B96: ARS | C96: 0 | D96: =IF(B96="USD",IF(G96="SI",C96/1.21,C96),IF(B$86>0,IF(G96="SI",C96/1.21,C96)/B$86,0)) -> 0 | E96: =IF(B96="ARS",IF(G96="SI",C96/1.21,C96),IF(G96="SI",C96/1.21,C96)*B$86) -> 0 | F96: PESO | G96: NO
A97: Honorarios despachante | B97: USD | C97: 0 | D97: =IF(B97="USD",IF(G97="SI",C97/1.21,C97),IF(B$86>0,IF(G97="SI",C97/1.21,C97)/B$86,0)) -> 0 | E97: =IF(B97="ARS",IF(G97="SI",C97/1.21,C97),IF(G97="SI",C97/1.21,C97)*B$86) -> 0 | F97: FOB | G97: NO
A98: Honorarios consultora | B98: USD | C98: 0 | D98: =IF(B98="USD",IF(G98="SI",C98/1.21,C98),IF(B$86>0,IF(G98="SI",C98/1.21,C98)/B$86,0)) -> 0 | E98: =IF(B98="ARS",IF(G98="SI",C98/1.21,C98),IF(G98="SI",C98/1.21,C98)*B$86) -> 0 | F98: FOB | G98: NO
B99: USD | C99: 0 | D99: =IF(B99="USD",IF(G99="SI",C99/1.21,C99),IF(B$86>0,IF(G99="SI",C99/1.21,C99)/B$86,0)) -> 0 | E99: =IF(B99="ARS",IF(G99="SI",C99/1.21,C99),IF(G99="SI",C99/1.21,C99)*B$86) -> 0 | F99: PESO | G99: NO
B100: USD | C100: 0 | D100: =IF(B100="USD",IF(G100="SI",C100/1.21,C100),IF(B$86>0,IF(G100="SI",C100/1.21,C100)/B$86,0)) -> 0 | E100: =IF(B100="ARS",IF(G100="SI",C100/1.21,C100),IF(G100="SI",C100/1.21,C100)*B$86) -> 0 | F100: PESO | G100: NO
B101: USD | C101: 0 | D101: =IF(B101="USD",IF(G101="SI",C101/1.21,C101),IF(B$86>0,IF(G101="SI",C101/1.21,C101)/B$86,0)) -> 0 | E101: =IF(B101="ARS",IF(G101="SI",C101/1.21,C101),IF(G101="SI",C101/1.21,C101)*B$86) -> 0 | F101: PESO | G101: NO
B102: USD | C102: 0 | D102: =IF(B102="USD",IF(G102="SI",C102/1.21,C102),IF(B$86>0,IF(G102="SI",C102/1.21,C102)/B$86,0)) -> 0 | E102: =IF(B102="ARS",IF(G102="SI",C102/1.21,C102),IF(G102="SI",C102/1.21,C102)*B$86) -> 0 | F102: PESO | G102: NO
A103: SUBTOTAL OPERATIVOS | D103: =SUM(D88:D102) -> 0 | E103: =SUM(E88:E102) -> 0
A104: Prorrateo operativos | B104: Por valor (FOB): | C104: =SUMPRODUCT((F88:F102="FOB")*D88:D102) -> 0 | D104: Por peso/vol: | E104: =SUMPRODUCT((F88:F102="PESO")*D88:D102) -> 0 | F104: Total: | G104: =C104+E104 -> 0
A106: IVA TERCEROS
A107: Concepto | B107: %IVA | C107: IVA USD | D107: IVA ARS
A108: =A88 -> Flete | B108: 0 | C108: =IF(B108>0,IF(G88="SI",IF(B88="USD",C88-D88,(C88-E88)/B$86),D88*B108),0) -> 0 | D108: =IF(B108>0,IF(G88="SI",IF(B88="ARS",C88-E88,(C88-D88)*B$86),E88*B108),0) -> 0
A109: =A89 -> Seguro | B109: 0.21 | C109: =IF(B109>0,IF(G89="SI",IF(B89="USD",C89-D89,(C89-E89)/B$86),D89*B109),0) -> 0 | D109: =IF(B109>0,IF(G89="SI",IF(B89="ARS",C89-E89,(C89-D89)*B$86),E89*B109),0) -> 0
A110: =A90 -> Gastos EXW | B110: 0 | C110: =IF(B110>0,IF(G90="SI",IF(B90="USD",C90-D90,(C90-E90)/B$86),D90*B110),0) -> 0 | D110: =IF(B110>0,IF(G90="SI",IF(B90="ARS",C90-E90,(C90-D90)*B$86),E90*B110),0) -> 0
A111: =A91 -> Gastos locales | B111: 0.21 | C111: =IF(B111>0,IF(G91="SI",IF(B91="USD",C91-D91,(C91-E91)/B$86),D91*B111),0) -> 0 | D111: =IF(B111>0,IF(G91="SI",IF(B91="ARS",C91-E91,(C91-D91)*B$86),E91*B111),0) -> 0
A112: =A92 -> Terminal portuaria | B112: 0.21 | C112: =IF(B112>0,IF(G92="SI",IF(B92="USD",C92-D92,(C92-E92)/B$86),D92*B112),0) -> 0 | D112: =IF(B112>0,IF(G92="SI",IF(B92="ARS",C92-E92,(C92-D92)*B$86),E92*B112),0) -> 0
A113: =A93 -> Depósito fiscal | B113: 0.21 | C113: =IF(B113>0,IF(G93="SI",IF(B93="USD",C93-D93,(C93-E93)/B$86),D93*B113),0) -> 0 | D113: =IF(B113>0,IF(G93="SI",IF(B93="ARS",C93-E93,(C93-D93)*B$86),E93*B113),0) -> 0
A114: =A94 -> Gastos adicionales | B114: 0.21 | C114: =IF(B114>0,IF(G94="SI",IF(B94="USD",C94-D94,(C94-E94)/B$86),D94*B114),0) -> 0 | D114: =IF(B114>0,IF(G94="SI",IF(B94="ARS",C94-E94,(C94-D94)*B$86),E94*B114),0) -> 0
...

Sheet Costeo
A1: COSTO POR PRODUCTO
A2: Producto | B2: Costo FOB | C2: Imp+Gas Prorr | D2: Costo c/IVA | E2: s/IVA y Perc. | F2: c/IVA ARS | G2: s/IVA y Perc. ARS | H2: Nota
A3: =Presupuesto!A18 | B3: =IF(Presupuesto!D18>0,Presupuesto!C18+Presupuesto!E34*(Presupuesto!E18/Presupuesto!E$33)/Presupuesto!D18,0) -> 0 | C3: =IF(Presupuesto!D18>0,(Presupuesto!I45+Presupuesto!K65+Presupuesto!B$81*(Presupuesto!E18/Presupuesto!E$33)+Presupuesto!C$104*(Presupuesto!E18/Presupuesto!E$33)+Presupuesto!E$104*(IF(Presupuesto!I$33>0,Presupuesto!I18/Presupuesto!I$33,Presupuesto!E18/Presupuesto!E$33))+Presupuesto!C123*(Presupuesto!E18/Presupuesto!E$33))/Presupuesto!D18,0) -> 0 | D3: =B3+C3 -> 0 | E3: =IF(Presupuesto!D18>0,D3-(Presupuesto!D65+Presupuesto!F65+Presupuesto!H65+Presupuesto!J65+Presupuesto!C123*(Presupuesto!E18/Presupuesto!E$33))/Presupuesto!D18,0) -> 0 | F3: =D3*Presupuesto!B$86 -> 0 | G3: =E3*Presupuesto!B$86 -> 0
A4: =Presupuesto!A19 | B4: =IF(Presupuesto!D19>0,Presupuesto!C19+Presupuesto!E34*(Presupuesto!E19/Presupuesto!E$33)/Presupuesto!D19,0) -> 0 | C4: =IF(Presupuesto!D19>0,(Presupuesto!I46+Presupuesto!K66+Presupuesto!B$81*(Presupuesto!E19/Presupuesto!E$33)+Presupuesto!C$104*(Presupuesto!E19/Presupuesto!E$33)+Presupuesto!E$104*(IF(Presupuesto!I$33>0,Presupuesto!I19/Presupuesto!I$33,Presupuesto!E19/Presupuesto!E$33))+Presupuesto!C123*(Presupuesto!E19/Presupuesto!E$33))/Presupuesto!D19,0) -> 0 | D4: =B4+C4 -> 0 | E4: =IF(Presupuesto!D19>0,D4-(Presupuesto!D66+Presupuesto!F66+Presupuesto!H66+Presupuesto!J66+Presupuesto!C123*(Presupuesto!E19/Presupuesto!E$33))/Presupuesto!D19,0) -> 0 | F4: =D4*Presupuesto!B$86 -> 0 | G4: =E4*Presupuesto!B$86 -> 0
A5: =Presupuesto!A20 | B5: =IF(Presupuesto!D20>0,Presupuesto!C20+Presupuesto!E34*(Presupuesto!E20/Presupuesto!E$33)/Presupuesto!D20,0) -> 0 | C5: =IF(Presupuesto!D20>0,(Presupuesto!I47+Presupuesto!K67+Presupuesto!B$81*(Presupuesto!E20/Presupuesto!E$33)+Presupuesto!C$104*(Presupuesto!E20/Presupuesto!E$33)+Presupuesto!E$104*(IF(Presupuesto!I$33>0,Presupuesto!I20/Presupuesto!I$33,Presupuesto!E20/Presupuesto!E$33))+Presupuesto!C123*(Presupuesto!E20/Presupuesto!E$33))/Presupuesto!D20,0) -> 0 | D5: =B5+C5 -> 0 | E5: =IF(Presupuesto!D20>0,D5-(Presupuesto!D67+Presupuesto!F67+Presupuesto!H67+Presupuesto!J67+Presupuesto!C123*(Presupuesto!E20/Presupuesto!E$33))/Presupuesto!D20,0) -> 0 | F5: =D5*Presupuesto!B$86 -> 0 | G5: =E5*Presupuesto!B$86 -> 0
A6: =Presupuesto!A21 | B6: =IF(Presupuesto!D21>0,Presupuesto!C21+Presupuesto!E34*(Presupuesto!E21/Presupuesto!E$33)/Presupuesto!D21,0) -> 0 | C6: =IF(Presupuesto!D21>0,(Presupuesto!I48+Presupuesto!K68+Presupuesto!B$81*(Presupuesto!E21/Presupuesto!E$33)+Presupuesto!C$104*(Presupuesto!E21/Presupuesto!E$33)+Presupuesto!E$104*(IF(Presupuesto!I$33>0,Presupuesto!I21/Presupuesto!I$33,Presupuesto!E21/Presupuesto!E$33))+Presupuesto!C123*(Presupuesto!E21/Presupuesto!E$33))/Presupuesto!D21,0) -> 0 | D6: =B6+C6 -> 0 | E6: =IF(Presupuesto!D21>0,D6-(Presupuesto!D68+Presupuesto!F68+Presupuesto!H68+Presupuesto!J68+Presupuesto!C123*(Presupuesto!E21/Presupuesto!E$33))/Presupuesto!D21,0) -> 0 | F6: =D6*Presupuesto!B$86 -> 0 | G6: =E6*Presupuesto!B$86 -> 0
A7: =Presupuesto!A22 | B7: =IF(Presupuesto!D22>0,Presupuesto!C22+Presupuesto!E34*(Presupuesto!E22/Presupuesto!E$33)/Presupuesto!D22,0) -> 0 | C7: =IF(Presupuesto!D22>0,(Presupuesto!I49+Presupuesto!K69+Presupuesto!B$81*(Presupuesto!E22/Presupuesto!E$33)+Presupuesto!C$104*(Presupuesto!E22/Presupuesto!E$33)+Presupuesto!E$104*(IF(Presupuesto!I$33>0,Presupuesto!I22/Presupuesto!I$33,Presupuesto!E22/Presupuesto!E$33))+Presupuesto!C123*(Presupuesto!E22/Presupuesto!E$33))/Presupuesto!D22,0) -> 0 | D7: =B7+C7 -> 0 | E7: =IF(Presupuesto!D22>0,D7-(Presupuesto!D69+Presupuesto!F69+Presupuesto!H69+Presupuesto!J69+Presupuesto!C123*(Presupuesto!E22/Presupuesto!E$33))/Presupuesto!D22,0) -> 0 | F7: =D7*Presupuesto!B$86 -> 0 | G7: =E7*Presupuesto!B$86 -> 0
A8: =Presupuesto!A23 | B8: =IF(Presupuesto!D23>0,Presupuesto!C23+Presupuesto!E34*(Presupuesto!E23/Presupuesto!E$33)/Presupuesto!D23,0) -> 0 | C8: =IF(Presupuesto!D23>0,(Presupuesto!I50+Presupuesto!K70+Presupuesto!B$81*(Presupuesto!E23/Presupuesto!E$33)+Presupuesto!C$104*(Presupuesto!E23/Presupuesto!E$33)+Presupuesto!E$104*(IF(Presupuesto!I$33>0,Presupuesto!I23/Presupuesto!I$33,Presupuesto!E23/Presupuesto!E$33))+Presupuesto!C123*(Presupuesto!E23/Presupuesto!E$33))/Presupuesto!D23,0) -> 0 | D8: =B8+C8 -> 0 | E8: =IF(Presupuesto!D23>0,D8-(Presupuesto!D70+Presupuesto!F70+Presupuesto!H70+Presupuesto!J70+Presupuesto!C123*(Presupuesto!E23/Presupuesto!E$33))/Presupuesto!D23,0) -> 0 | F8: =D8*Presupuesto!B$86 -> 0 | G8: =E8*Presupuesto!B$86 -> 0
A9: =Presupuesto!A24 | B9: =IF(Presupuesto!D24>0,Presupuesto!C24+Presupuesto!E34*(Presupuesto!E24/Presupuesto!E$33)/Presupuesto!D24,0) -> 0 | C9: =IF(Presupuesto!D24>0,(Presupuesto!I51+Presupuesto!K71+Presupuesto!B$81*(Presupuesto!E24/Presupuesto!E$33)+Presupuesto!C$104*(Presupuesto!E24/Presupuesto!E$33)+Presupuesto!E$104*(IF(Presupuesto!I$33>0,Presupuesto!I24/Presupuesto!I$33,Presupuesto!E24/Presupuesto!E$33))+Presupuesto!C123*(Presupuesto!E24/Presupuesto!E$33))/Presupuesto!D24,0) -> 0 | D9: =B9+C9 -> 0 | E9: =IF(Presupuesto!D24>0,D9-(Presupuesto!D71+Presupuesto!F71+Presupuesto!H71+Presupuesto!J71+Presupuesto!C123*(Presupuesto!E24/Presupuesto!E$33))/Presupuesto!D24,0) -> 0 | F9: =D9*Presupuesto!B$86 -> 0 | G9: =E9*Presupuesto!B$86 -> 0
A10: =Presupuesto!A25 | B10: =IF(Presupuesto!D25>0,Presupuesto!C25+Presupuesto!E34*(Presupuesto!E25/Presupuesto!E$33)/Presupuesto!D25,0) -> 0 | C10: =IF(Presupuesto!D25>0,(Presupuesto!I52+Presupuesto!K72+Presupuesto!B$81*(Presupuesto!E25/Presupuesto!E$33)+Presupuesto!C$104*(Presupuesto!E25/Presupuesto!E$33)+Presupuesto!E$104*(IF(Presupuesto!I$33>0,Presupuesto!I25/Presupuesto!I$33,Presupuesto!E25/Presupuesto!E$33))+Presupuesto!C123*(Presupuesto!E25/Presupuesto!E$33))/Presupuesto!D25,0) -> 0 | D10: =B10+C10 -> 0 | E10: =IF(Presupuesto!D25>0,D10-(Presupuesto!D72+Presupuesto!F72+Presupuesto!H72+Presupuesto!J72+Presupuesto!C123*(Presupuesto!E25/Presupuesto!E$33))/Presupuesto!D25,0) -> 0 | F10: =D10*Presupuesto!B$86 -> 0 | G10: =E10*Presupuesto!B$86 -> 0
A11: =Presupuesto!A26 | B11: =IF(Presupuesto!D26>0,Presupuesto!C26+Presupuesto!E34*(Presupuesto!E26/Presupuesto!E$33)/Presupuesto!D26,0) -> 0 | C11: =IF(Presupuesto!D26>0,(Presupuesto!I53+Presupuesto!K73+Presupuesto!B$81*(Presupuesto!E26/Presupuesto!E$33)+Presupuesto!C$104*(Presupuesto!E26/Presupuesto!E$33)+Presupuesto!E$104*(IF(Presupuesto!I$33>0,Presupuesto!I26/Presupuesto!I$33,Presupuesto!E26/Presupuesto!E$33))+Presupuesto!C123*(Presupuesto!E26/Presupuesto!E$33))/Presupuesto!D26,0) -> 0 | D11: =B11+C11 -> 0 | E11: =IF(Presupuesto!D26>0,D11-(Presupuesto!D73+Presupuesto!F73+Presupuesto!H73+Presupuesto!J73+Presupuesto!C123*(Presupuesto!E26/Presupuesto!E$33))/Presupuesto!D26,0) -> 0 | F11: =D11*Presupuesto!B$86 -> 0 | G11: =E11*Presupuesto!B$86 -> 0
A12: =Presupuesto!A27 | B12: =IF(Presupuesto!D27>0,Presupuesto!C27+Presupuesto!E34*(Presupuesto!E27/Presupuesto!E$33)/Presupuesto!D27,0) -> 0 | C12: =IF(Presupuesto!D27>0,(Presupuesto!I54+Presupuesto!K74+Presupuesto!B$81*(Presupuesto!E27/Presupuesto!E$33)+Presupuesto!C$104*(Presupuesto!E27/Presupuesto!E$33)+Presupuesto!E$104*(IF(Presupuesto!I$33>0,Presupuesto!I27/Presupuesto!I$33,Presupuesto!E27/Presupuesto!E$33))+Presupuesto!C123*(Presupuesto!E27/Presupuesto!E$33))/Presupuesto!D27,0) -> 0 | D12: =B12+C12 -> 0 | E12: =IF(Presupuesto!D27>0,D12-(Presupuesto!D74+Presupuesto!F74+Presupuesto!H74+Presupuesto!J74+Presupuesto!C123*(Presupuesto!E27/Presupuesto!E$33))/Presupuesto!D27,0) -> 0 | F12: =D12*Presupuesto!B$86 -> 0 | G12: =E12*Presupuesto!B$86 -> 0
A13: =Presupuesto!A28 | B13: =IF(Presupuesto!D28>0,Presupuesto!C28+Presupuesto!E34*(Presupuesto!E28/Presupuesto!E$33)/Presupuesto!D28,0) -> 0 | C13: =IF(Presupuesto!D28>0,(Presupuesto!I55+Presupuesto!K75+Presupuesto!B$81*(Presupuesto!E28/Presupuesto!E$33)+Presupuesto!C$104*(Presupuesto!E28/Presupuesto!E$33)+Presupuesto!E$104*(IF(Presupuesto!I$33>0,Presupuesto!I28/Presupuesto!I$33,Presupuesto!E28/Presupuesto!E$33))+Presupuesto!C123*(Presupuesto!E28/Presupuesto!E$33))/Presupuesto!D28,0) -> 0 | D13: =B13+C13 -> 0 | E13: =IF(Presupuesto!D28>0,D13-(Presupuesto!D75+Presupuesto!F75+Presupuesto!H75+Presupuesto!J75+Presupuesto!C123*(Presupuesto!E28/Presupuesto!E$33))/Presupuesto!D28,0) -> 0 | F13: =D13*Presupuesto!B$86 -> 0 | G13: =E13*Presupuesto!B$86 -> 0
A14: =Presupuesto!A29 | B14: =IF(Presupuesto!D29>0,Presupuesto!C29+Presupuesto!E34*(Presupuesto!E29/Presupuesto!E$33)/Presupuesto!D29,0) -> 0 | C14: =IF(Presupuesto!D29>0,(Presupuesto!I56+Presupuesto!K76+Presupuesto!B$81*(Presupuesto!E29/Presupuesto!E$33)+Presupuesto!C$104*(Presupuesto!E29/Presupuesto!E$33)+Presupuesto!E$104*(IF(Presupuesto!I$33>0,Presupuesto!I29/Presupuesto!I$33,Presupuesto!E29/Presupuesto!E$33))+Presupuesto!C123*(Presupuesto!E29/Presupuesto!E$33))/Presupuesto!D29,0) -> 0 | D14: =B14+C14 -> 0 | E14: =IF(Presupuesto!D29>0,D14-(Presupuesto!D76+Presupuesto!F76+Presupuesto!H76+Presupuesto!J76+Presupuesto!C123*(Presupuesto!E29/Presupuesto!E$33))/Presupuesto!D29,0) -> 0 | F14: =D14*Presupuesto!B$86 -> 0 | G14: =E14*Presupuesto!B$86 -> 0
A15: =Presupuesto!A30 | B15: =IF(Presupuesto!D30>0,Presupuesto!C30+Presupuesto!E34*(Presupuesto!E30/Presupuesto!E$33)/Presupuesto!D30,0) -> 0 | C15: =IF(Presupuesto!D30>0,(Presupuesto!I57+Presupuesto!K77+Presupuesto!B$81*(Presupuesto!E30/Presupuesto!E$33)+Presupuesto!C$104*(Presupuesto!E30/Presupuesto!E$33)+Presupuesto!E$104*(IF(Presupuesto!I$33>0,Presupuesto!I30/Presupuesto!I$33,Presupuesto!E30/Presupuesto!E$33))+Presupuesto!C123*(Presupuesto!E30/Presupuesto!E$33))/Presupuesto!D30,0) -> 0 | D15: =B15+C15 -> 0 | E15: =IF(Presupuesto!D30>0,D15-(Presupuesto!D77+Presupuesto!F77+Presupuesto!H77+Presupuesto!J77+Presupuesto!C123*(Presupuesto!E30/Presupuesto!E$33))/Presupuesto!D30,0) -> 0 | F15: =D15*Presupuesto!B$86 -> 0 | G15: =E15*Presupuesto!B$86 -> 0
A16: =Presupuesto!A31 | B16: =IF(Presupuesto!D31>0,Presupuesto!C31+Presupuesto!E34*(Presupuesto!E31/Presupuesto!E$33)/Presupuesto!D31,0) -> 0 | C16: =IF(Presupuesto!D31>0,(Presupuesto!I58+Presupuesto!K78+Presupuesto!B$81*(Presupuesto!E31/Presupuesto!E$33)+Presupuesto!C$104*(Presupuesto!E31/Presupuesto!E$33)+Presupuesto!E$104*(IF(Presupuesto!I$33>0,Presupuesto!I31/Presupuesto!I$33,Presupuesto!E31/Presupuesto!E$33))+Presupuesto!C123*(Presupuesto!E31/Presupuesto!E$33))/Presupuesto!D31,0) -> 0 | D16: =B16+C16 -> 0 | E16: =IF(Presupuesto!D31>0,D16-(Presupuesto!D78+Presupuesto!F78+Presupuesto!H78+Presupuesto!J78+Presupuesto!C123*(Presupuesto!E31/Presupuesto!E$33))/Presupuesto!D31,0) -> 0 | F16: =D16*Presupuesto!B$86 -> 0 | G16: =E16*Presupuesto!B$86 -> 0
A17: =Presupuesto!A32 | B17: =IF(Presupuesto!D32>0,Presupuesto!C32+Presupuesto!E34*(Presupuesto!E32/Presupuesto!E$33)/Presupuesto!D32,0) -> 0 | C17: =IF(Presupuesto!D32>0,(Presupuesto!I59+Presupuesto!K79+Presupuesto!B$81*(Presupuesto!E32/Presupuesto!E$33)+Presupuesto!C$104*(Presupuesto!E32/Presupuesto!E$33)+Presupuesto!E$104*(IF(Presupuesto!I$33>0,Presupuesto!I32/Presupuesto!I$33,Presupuesto!E32/Presupuesto!E$33))+Presupuesto!C123*(Presupuesto!E32/Presupuesto!E$33))/Presupuesto!D32,0) -> 0 | D17: =B17+C17 -> 0 | E17: =IF(Presupuesto!D32>0,D17-(Presupuesto!D79+Presupuesto!F79+Presupuesto!H79+Presupuesto!J79+Presupuesto!C123*(Presupuesto!E32/Presupuesto!E$33))/Presupuesto!D32,0) -> 0 | F17: =D17*Presupuesto!B$86 -> 0 | G17: =E17*Presupuesto!B$86 -> 0
A18: TOTAL | D18: =D3*Presupuesto!D18+D4*Presupuesto!D19+D5*Presupuesto!D20+D6*Presupuesto!D21+D7*Presupuesto!D22+D8*Presupuesto!D23+D9*Presupuesto!D24+D10*Presupuesto!D25+D11*Presupuesto!D26+D12*Presupuesto!D27+D13*Presupuesto!D28+D14*Presupuesto!D29+D15*Presupuesto!D30+D16*Presupuesto!D31+D17*Presupuesto!D32 -> 0
A19: CHECK (debe ser $0) | B19: =Presupuesto!B126-(D3*Presupuesto!D18+D4*Presupuesto!D19+D5*Presupuesto!D20+D6*Presupuesto!D21+D7*Presupuesto!D22+D8*Presupuesto!D23+D9*Presupuesto!D24+D10*Presupuesto!D25+D11*Presupuesto!D26+D12*Presupuesto!D27+D13*Presupuesto!D28+D14*Presupuesto!D29+D15*Presupuesto!D30+D16*Presupuesto!D31+D17*Presupuesto!D32) -> 10
A21: SIMULACIÓN DE VENTA (USD)
A22: Producto | B22: Costo c/IVA | C22: Margen % | D22: PV Sugerido | E22: PV Final | F22: PV Mercado | G22: Margen Real % | H22: Ganancia Unit
A23: =Presupuesto!A18 | B23: =D3 -> 0 | C23: 0.3 | D23: =B23*(1+C23) -> 0 | E23: 0 | F23: 0 | G23: =IF(AND(B23>0,E23>0),(E23-B23)/B23,0) -> 0 | H23: =IF(E23>0,E23-B23,0) -> 0
A24: =Presupuesto!A19 | B24: =D4 -> 0 | C24: 0.3 | D24: =B24*(1+C24) -> 0 | E24: 0 | F24: 0 | G24: =IF(AND(B24>0,E24>0),(E24-B24)/B24,0) -> 0 | H24: =IF(E24>0,E24-B24,0) -> 0
A25: =Presupuesto!A20 | B25: =D5 -> 0 | C25: 0.3 | D25: =B25*(1+C25) -> 0 | E25: 0 | F25: 0 | G25: =IF(AND(B25>0,E25>0),(E25-B25)/B25,0) -> 0 | H25: =IF(E25>0,E25-B25,0) -> 0
A26: =Presupuesto!A21 | B26: =D6 -> 0 | C26: 0.3 | D26: =B26*(1+C26) -> 0 | E26: 0 | F26: 0 | G26: =IF(AND(B26>0,E26>0),(E26-B26)/B26,0) -> 0 | H26: =IF(E26>0,E26-B26,0) -> 0
A27: =Presupuesto!A22 | B27: =D7 -> 0 | C27: 0.3 | D27: =B27*(1+C27) -> 0 | E27: 0 | F27: 0 | G27: =IF(AND(B27>0,E27>0),(E27-B27)/B27,0) -> 0 | H27: =IF(E27>0,E27-B27,0) -> 0
A28: =Presupuesto!A23 | B28: =D8 -> 0 | C28: 0.3 | D28: =B28*(1+C28) -> 0 | E28: 0 | F28: 0 | G28: =IF(AND(B28>0,E28>0),(E28-B28)/B28,0) -> 0 | H28: =IF(E28>0,E28-B28,0) -> 0
A29: =Presupuesto!A24 | B29: =D9 -> 0 | C29: 0.3 | D29: =B29*(1+C29) -> 0 | E29: 0 | F29: 0 | G29: =IF(AND(B29>0,E29>0),(E29-B29)/B29,0) -> 0 | H29: =IF(E29>0,E29-B29,0) -> 0
A30: =Presupuesto!A25 | B30: =D10 -> 0 | C30: 0.3 | D30: =B30*(1+C30) -> 0 | E30: 0 | F30: 0 | G30: =IF(AND(B30>0,E30>0),(E30-B30)/B30,0) -> 0 | H30: =IF(E30>0,E30-B30,0) -> 0
A31: =Presupuesto!A26 | B31: =D11 -> 0 | C31: 0.3 | D31: =B31*(1+C31) -> 0 | E31: 0 | F31: 0 | G31: =IF(AND(B31>0,E31>0),(E31-B31)/B31,0) -> 0 | H31: =IF(E31>0,E31-B31,0) -> 0
A32: =Presupuesto!A27 | B32: =D12 -> 0 | C32: 0.3 | D32: =B32*(1+C32) -> 0 | E32: 0 | F32: 0 | G32: =IF(AND(B32>0,E32>0),(E32-B32)/B32,0) -> 0 | H32: =IF(E32>0,E32-B32,0) -> 0
A33: =Presupuesto!A28 | B33: =D13 -> 0 | C33: 0.3 | D33: =B33*(1+C33) -> 0 | E33: 0 | F33: 0 | G33: =IF(AND(B33>0,E33>0),(E33-B33)/B33,0) -> 0 | H33: =IF(E33>0,E33-B33,0) -> 0
A34: =Presupuesto!A29 | B34: =D14 -> 0 | C34: 0.3 | D34: =B34*(1+C34) -> 0 | E34: 0 | F34: 0 | G34: =IF(AND(B34>0,E34>0),(E34-B34)/B34,0) -> 0 | H34: =IF(E34>0,E34-B34,0) -> 0
... A37: =Presupuesto!A32 | B37: =D17 -> 0 | C37: 0.3 | D37: =B37*(1+C37) -> 0 | E37: 0 | F37: 0 | G37: =IF(AND(B37>0,E37>0),(E37-B37)/B37,0) -> 0 | H37: =IF(E37>0,E37-B37,0) -> 0
A39: SIMULACIÓN DE VENTA (ARS)
A40: TC Venta ARS: | B40: 0
A41: Producto | B41: Costo c/IVA | C41: Margen % | D41: PV Sugerido | E41: PV Final | F41: PV Mercado | G41: Margen Real % | H41: Ganancia Unit
A42: =Presupuesto!A18 | B42: =F3 -> 0 | C42: =C23 -> 0.3 | D42: =B42*(1+C42) -> 0 | E42: =IF(B$40>0,E23*B$40,0) -> 0 | F42: =IF(B$40>0,F23*B$40,0) -> 0 | G42: =IF(AND(B42>0,E42>0),(E42-B42)/B42,0) -> 0 | H42: =IF(E42>0,E42-B42,0) -> 0
A43: =Presupuesto!A19 | B43: =F4 -> 0 | C43: =C24 -> 0.3 | D43: =B43*(1+C43) -> 0 | E43: =IF(B$40>0,E24*B$40,0) -> 0 | F43: =IF(B$40>0,F24*B$40,0) -> 0 | G43: =IF(AND(B43>0,E43>0),(E43-B43)/B43,0) -> 0 | H43: =IF(E43>0,E43-B43,0) -> 0
A44: =Presupuesto!A20 | B44: =F5 -> 0 | C44: =C25 -> 0.3 | D44: =B44*(1+C44) -> 0 | E44: =IF(B$40>0,E25*B$40,0) -> 0 | F44: =IF(B$40>0,F25*B$40,0) -> 0 | G44: =IF(AND(B44>0,E44>0),(E44-B44)/B44,0) -> 0 | H44: =IF(E44>0,E44-B44,0) -> 0
A45: =Presupuesto!A21 | B45: =F6 -> 0 | C45: =C26 -> 0.3 | D45: =B45*(1+C45) -> 0 | E45: =IF(B$40>0,E26*B$40,0) -> 0 | F45: =IF(B$40>0,F26*B$40,0) -> 0 | G45: =IF(AND(B45>0,E45>0),(E45-B45)/B45,0) -> 0 | H45: =IF(E45>0,E45-B45,0) -> 0
A46: =Presupuesto!A22 | B46: =F7 -> 0 | C46: =C27 -> 0.3 | D46: =B46*(1+C46) -> 0 | E46: =IF(B$40>0,E27*B$40,0) -> 0 | F46: =IF(B$40>0,F27*B$40,0) -> 0 | G46: =IF(AND(B46>0,E46>0),(E46-B46)/B46,0) -> 0 | H46: =IF(E46>0,E46-B46,0) -> 0
A47: =Presupuesto!A23 | B47: =F8 -> 0 | C47: =C28 -> 0.3 | D47: =B47*(1+C47) -> 0 | E47: =IF(B$40>0,E28*B$40,0) -> 0 | F47: =IF(B$40>0,F28*B$40,0) -> 0 | G47: =IF(AND(B47>0,E47>0),(E47-B47)/B47,0) -> 0 | H47: =IF(E47>0,E47-B47,0) -> 0
A48: =Presupuesto!A24 | B48: =F9 -> 0 | C48: =C29 -> 0.3 | D48: =B48*(1+C48) -> 0 | E48: =IF(B$40>0,E29*B$40,0) -> 0 | F48: =IF(B$40>0,F29*B$40,0) -> 0 | G48: =IF(AND(B48>0,E48>0),(E48-B48)/B48,0) -> 0 | H48: =IF(E48>0,E48-B48,0) -> 0
A49: =Presupuesto!A25 | B49: =F10 -> 0 | C49: =C30 -> 0.3 | D49: =B49*(1+C49) -> 0 | E49: =IF(B$40>0,E30*B$40,0) -> 0 | F49: =IF(B$40>0,F30*B$40,0) -> 0 | G49: =IF(AND(B49>0,E49>0),(E49-B49)/B49,0) -> 0 | H49: =IF(E49>0,E49-B49,0) -> 0
A50: =Presupuesto!A26 | B50: =F11 -> 0 | C50: =C31 -> 0.3 | D50: =B50*(1+C50) -> 0 | E50: =IF(B$40>0,E31*B$40,0) -> 0 | F50: =IF(B$40>0,F31*B$40,0) -> 0 | G50: =IF(AND(B50>0,E50>0),(E50-B50)/B50,0) -> 0 | H50: =IF(E50>0,E50-B50,0) -> 0
A51: =Presupuesto!A27 | B51: =F12 -> 0 | C51: =C32 -> 0.3 | D51: =B51*(1+C51) -> 0 | E51: =IF(B$40>0,E32*B$40,0) -> 0 | F51: =IF(B$40>0,F32*B$40,0) -> 0 | G51: =IF(AND(B51>0,E51>0),(E51-B51)/B51,0) -> 0 | H51: =IF(E51>0,E51-B51,0) -> 0
A52: =Presupuesto!A28 | B52: =F13 -> 0 | C52: =C33 -> 0.3 | D52: =B52*(1+C52) -> 0 | E52: =IF(B$40>0,E33*B$40,0) -> 0 | F52: =IF(B$40>0,F33*B$40,0) -> 0 | G52: =IF(AND(B52>0,E52>0),(E52-B52)/B52,0) -> 0 | H52: =IF(E52>0,E52-B52,0) -> 0
A53: =Presupuesto!A29 | B53: =F14 -> 0 | C53: =C34 -> 0.3 | D53: =B53*(1+C53) -> 0 | E53: =IF(B$40>0,E34*B$40,0) -> 0 | F53: =IF(B$40>0,F34*B$40,0) -> 0 | G53: =IF(AND(B53>0,E53>0),(E53-B53)/B53,0) -> 0 | H53: =IF(E53>0,E53-B53,0) -> 0
... A56: =Presupuesto!A32 | B56: =F17 -> 0 | C56: =C37 -> 0.3 | D56: =B56*(1+C56) -> 0 | E56: =IF(B$40>0,E37*B$40,0) -> 0 | F56: =IF(B$40>0,F37*B$40,0) -> 0 | G56: =IF(AND(B56>0,E56>0),(E56-B56)/B56,0) -> 0 | H56: =IF(E56>0,E56-B56,0) -> 0
A58: PERCEPCIONES Y CRÉDITOS FISCALES
A59: Concepto | B59: USD | C59: ARS
A60: IVA (crédito fiscal) | B60: =Presupuesto!D80 -> 0 | C60: =B60*Presupuesto!B$37 -> 0
A61: IVA Adicional | B61: =Presupuesto!F80 -> 0 | C61: =B61*Presupuesto!B$37 -> 0
A62: IVA Terceros | B62: =Presupuesto!C123 -> 0 | C62: =B62*Presupuesto!B$37 -> 0
A63: Ganancias (percepción) | B63: =Presupuesto!H80 -> 0 | C63: =B63*Presupuesto!B$37 -> 0
A64: IIBB (percepción) | B64: =Presupuesto!J80 -> 0 | C64: =B64*Presupuesto!B$37 -> 0
A65: Total percepciones | B65: =SUM(B60:B64) -> 0 | C65: =SUM(C60:C64) -> 0
A67: RESULTADO DE LA OPERACIÓN
B68: USD | C68: ARS
A69: Inversión total (c/IVA) | B69: =Presupuesto!B126 -> 10 | C69: =Presupuesto!C126 -> 15100
A70: Venta total estimada | B70: =E23*Presupuesto!D18+E24*Presupuesto!D19+E25*Presupuesto!D20+E26*Presupuesto!D21+E27*Presupuesto!D22+E28*Presupuesto!D23+E29*Presupuesto!D24+E30*Presupuesto!D25+E31*Presupuesto!D26+E32*Presupuesto!D27+E33*Presupuesto!D28+E34*Presupuesto!D29+E35*Presupuesto!D30+E36*Presupuesto!D31+E37*Presupuesto!D32 -> 0 | C70: =B70*Presupuesto!B$86 -> 0
A71: Ganancia bruta | B71: =IF(B70>0,B70-B69,0) -> 0 | C71: =IF(C70>0,C70-C69,0) -> 0
A72: IVA a recuperar | B72: =Presupuesto!D80+Presupuesto!F80+Presupuesto!C123 -> 0 | C72: =B72*Presupuesto!B$37 -> 0
A73: Percepciones a recuperar | B73: =Presupuesto!H80+Presupuesto!J80 -> 0 | C73: =B73*Presupuesto!B$37 -> 0
A74: % Rentabilidad s/inversión | B74: =IF(AND(B69>0,B70>0),B71/B69,0) -> 0 | C74: =IF(AND(C69>0,C70>0),C71/C69,0) -> 0
A76: CONCILIACIÓN DE PAGOS REALES
B77: Monto | C77: Moneda | D77: Fecha | E77: Ref/Comprobante
A78: Pago proveedor (mercadería) | B78: 0 | C78: USD
A79: VEP tributos (AFIP) | B79: 0 | C79: USD
A80: Gastos operativos | B80: 0 | C80: USD
A81: Intervenciones / Gastos adicionales | B81: 0 | C81: USD
A82: Otros pagos | B82: 0 | C82: USD
A83: TOTAL PAGADO REAL | B83: =IF(C78="USD",B78,IF(Presupuesto!B$86>0,B78/Presupuesto!B$86,0))+IF(C79="USD",B79,IF(Presupuesto!B$86>0,B79/Presupuesto!B$86,0))+IF(C80="USD",B80,IF(Presupuesto!B$86>0,B80/Presupuesto!B$86,0))+IF(C81="USD",B81,IF(Presupuesto!B$86>0,B81/Presupuesto!B$86,0))+IF(C82="USD",B82,IF(Presupuesto!B$86>0,B82/Presupuesto!B$86,0)) -> 0
A84: Total calculado | B84: =Presupuesto!B126 -> 10
A85: DIFERENCIA | B85: =B83-B84 -> -10 | C85: Debe ser $0
